ti_analyzer_python/__init__.py
ti_analyzer_python/analyzer.py
ti_analyzer_python/configuration.py
ti_analyzer_python/helpers/__init__.py
ti_analyzer_python/helpers/pycodestyle.ini
ti_analyzer_python/helpers/schema.py
ti_analyzer_python/helpers/teststyle_pep8.py
ti_analyzer_python/image_configuration.py
ti_analyzer_python/ti_object_models/__init__.py
ti_analyzer_python/ti_object_models/argument.py
ti_analyzer_python/ti_object_models/argument_types_enum.py
ti_analyzer_python/ti_object_models/exceptions.py
ti_analyzer_python/ti_object_models/file_specific_fields.py
ti_analyzer_python/ti_object_models/handshake.py
ti_analyzer_python/ti_object_models/network_artifact_specific_fields.py
ti_analyzer_python/ti_object_models/related_artifact.py
ti_analyzer_python/ti_object_models/relationship_type.py
ti_analyzer_python/ti_object_models/request.py
ti_analyzer_python/ti_object_models/response.py
ti_analyzer_python/ti_object_models/response_external.py
ti_analyzer_python/ti_object_models/ti_artifact_types.py
ti_analyzer_python-1.0.7.dist-info/METADATA
ti_analyzer_python-1.0.7.dist-info/WHEEL
ti_analyzer_python-1.0.7.dist-info/RECORD
