Metadata-Version: 2.1
Name: ti-analyzer-python
Version: 1.0.7
Summary: Library of analyzers for connection to RT Protect TI product
License: MIT
Author: RT Protect TI
Requires-Python: >=3.11,<4.0
Classifier: License :: OSI Approved :: MIT License
Classifier: Programming Language :: Python :: 3
Classifier: Programming Language :: Python :: 3.11
Classifier: Programming Language :: Python :: 3.12
Classifier: Programming Language :: Python :: 3.13
Requires-Dist: confluent-kafka (>=2.4.0,<2.5.0)
Requires-Dist: jsonschema (>=4.23.0,<4.24.0)
Requires-Dist: pydantic (>=2.10.2,<2.11.0)
Requires-Dist: pymongo (>=4.10.1,<4.11.0)
